easyfont/__init__.py
easyfont/_core.py
easyfont/_types.py
easyfont/fonts/NotoSans-Regular.ttf
easyfont/fonts/NotoSansSC-Regular.ttf
easyfont/fonts/NotoSansTC-Regular.ttf
easyfont-0.0.1.post10.dist-info/METADATA
easyfont-0.0.1.post10.dist-info/WHEEL
easyfont-0.0.1.post10.dist-info/top_level.txt
easyfont-0.0.1.post10.dist-info/RECORD
