Metadata-Version: 2.1
Name: easyfont
Version: 0.0.1.post10
Summary: One line of code, your ideal font is ready — EasyFont.
Author-email: ferretsprite <ferret-sprite-goon@duck.com>
Project-URL: Homepage, https://github.com/xx025/easyfont
Project-URL: Repository, https://github.com/xx025/easyfont
Project-URL: Documentation, https://github.com/xx025/easyfont#readme
Requires-Python: >=3.8
Requires-Dist: importlib-resources >=6.4.5
